examples/pipelines/dhis2/pipeline.py
examples/pipelines/iaso/pipeline.py
examples/pipelines/logistic_stats/pipeline.py
examples/pipelines/simple_io/pipeline.py
openhexa/cli/__init__.py
openhexa/cli/api.py
openhexa/cli/cli.py
openhexa/cli/settings.py
openhexa/cli/skeleton/.gitignore
openhexa/cli/skeleton/pipeline.py.j2
openhexa/cli/skeleton/workspace.yaml
openhexa/cli/skeleton/.github/workflows/push-pipeline.yml.j2
openhexa/cli/skeleton/.vscode/launch.json.j2
openhexa/graphql/__init__.py
openhexa/graphql/base_openhexa_client.py
openhexa/graphql/queries.graphql
openhexa/graphql/schema.generated.graphql
openhexa/graphql/graphql_client/__init__.py
openhexa/graphql/graphql_client/add_pipeline_recipient.py
openhexa/graphql/graphql_client/add_webapp_to_favorites.py
openhexa/graphql/graphql_client/archive_workspace.py
openhexa/graphql/graphql_client/async_base_client.py
openhexa/graphql/graphql_client/base_client.py
openhexa/graphql/graphql_client/base_model.py
openhexa/graphql/graphql_client/client.py
openhexa/graphql/graphql_client/create_connection.py
openhexa/graphql/graphql_client/create_dataset.py
openhexa/graphql/graphql_client/create_pipeline.py
openhexa/graphql/graphql_client/create_pipeline_from_template_version.py
openhexa/graphql/graphql_client/create_pipeline_template_version.py
openhexa/graphql/graphql_client/create_webapp.py
openhexa/graphql/graphql_client/create_workspace.py
openhexa/graphql/graphql_client/dataset.py
openhexa/graphql/graphql_client/datasets.py
openhexa/graphql/graphql_client/delete_connection.py
openhexa/graphql/graphql_client/delete_dataset.py
openhexa/graphql/graphql_client/delete_pipeline.py
openhexa/graphql/graphql_client/delete_pipeline_template.py
openhexa/graphql/graphql_client/delete_pipeline_version.py
openhexa/graphql/graphql_client/delete_webapp.py
openhexa/graphql/graphql_client/enums.py
openhexa/graphql/graphql_client/exceptions.py
openhexa/graphql/graphql_client/get_connection.py
openhexa_sdk-2.16.0.dist-info/licenses/LICENCE
openhexa_sdk-2.16.0.dist-info/METADATA
openhexa_sdk-2.16.0.dist-info/WHEEL
openhexa_sdk-2.16.0.dist-info/entry_points.txt
openhexa_sdk-2.16.0.dist-info/top_level.txt
openhexa_sdk-2.16.0.dist-info/RECORD
