Metadata-Version: 2.4
Name: openhexa.sdk
Version: 2.16.0
Summary: OpenHEXA SDK
Author-email: Bluesquare <dev@bluesquarehub.com>
Maintainer-email: Bluesquare <dev@bluesquarehub.com>
Project-URL: Homepage, https://github.com/blsq/openhexa-sdk-python
Project-URL: Bug Tracker, https://github.com/blsq/openhexa-sdk-python/issues
Classifier: Programming Language :: Python :: 3
Classifier: License :: OSI Approved :: MIT License
Classifier: Operating System :: OS Independent
Requires-Python: <3.15,>=3.11
License-File: LICENCE
Requires-Dist: urllib3<3
Requires-Dist: multiprocess~=0.70.15
Requires-Dist: requests<2.33,>=2.31
Requires-Dist: PyYAML~=6.0
Requires-Dist: click~=8.1.3
Requires-Dist: jinja2<4,>3
Requires-Dist: docker>=7
Requires-Dist: graphql-core<4,>3
Requires-Dist: ariadne-codegen<1,>=0.14.0
Provides-Extra: dev
Requires-Dist: ruff<0.15.0,>=0.14.0; extra == "dev"
Requires-Dist: pytest<10,>=9; extra == "dev"
Requires-Dist: build<2,>=1.3; extra == "dev"
Requires-Dist: pytest-cov<8,>=7; extra == "dev"
Requires-Dist: pre-commit; extra == "dev"
Requires-Dist: httmock; extra == "dev"
Provides-Extra: examples
Requires-Dist: geopandas<1.2.0,>=1.1.0; extra == "examples"
Requires-Dist: pandas<2.4,>=2.3; extra == "examples"
Requires-Dist: rasterio~=1.4.1; extra == "examples"
Requires-Dist: rasterstats<0.21,>=0.20; extra == "examples"
Requires-Dist: setuptools<80.10.0,>=80.9.0; extra == "examples"
Requires-Dist: SQLAlchemy~=2.0.9; extra == "examples"
Requires-Dist: psycopg2; extra == "examples"
Dynamic: license-file
